mirakuru/__init__.py
mirakuru/base.py
mirakuru/base_env.py
mirakuru/compat.py
mirakuru/exceptions.py
mirakuru/http.py
mirakuru/output.py
mirakuru/pid.py
mirakuru/py.typed
mirakuru/tcp.py
mirakuru/unixsocket.py
mirakuru-2.5.3.dist-info/AUTHORS.rst
mirakuru-2.5.3.dist-info/LICENSE
mirakuru-2.5.3.dist-info/METADATA
mirakuru-2.5.3.dist-info/WHEEL
mirakuru-2.5.3.dist-info/top_level.txt
mirakuru-2.5.3.dist-info/zip-safe
mirakuru-2.5.3.dist-info/RECORD
