Metadata-Version: 2.1
Name: mirakuru
Version: 2.5.3
Summary: Process executor (not only) for tests.
Author-email: Grzegorz Śliwiński <fizyk+pypi@fizyk.dev>
License:                    GNU LESSER GENERAL PUBLIC LICENSE
Project-URL: Source, https://github.com/ClearcodeHQ/mirakuru
Project-URL: Bug Tracker, https://github.com/ClearcodeHQ/mirakuru/issues
Project-URL: Changelog, https://github.com/ClearcodeHQ/mirakuru/blob/v2.5.3/CHANGES.rst
Keywords: process,executor,tests,orchestration
Classifier: Development Status :: 5 - Production/Stable
Classifier: Intended Audience :: Developers
Classifier: License :: OSI Approved :: GNU Lesser General Public License v3 or later (LGPLv3+)
Classifier: Natural Language :: English
Classifier: Operating System :: OS Independent
Classifier: Programming Language :: Python
Classifier: Programming Language :: Python :: 3
Classifier: Programming Language :: Python :: 3.9
Classifier: Programming Language :: Python :: 3.10
Classifier: Programming Language :: Python :: 3.11
Classifier: Programming Language :: Python :: 3.12
Classifier: Programming Language :: Python :: 3.13
Classifier: Programming Language :: Python :: 3 :: Only
Classifier: Topic :: Software Development :: Libraries :: Python Modules
Requires-Python: >=3.9
License-File: LICENSE
License-File: AUTHORS.rst
Requires-Dist: psutil>=4.0.0; sys_platform != "cygwin"
